rrmngmnt/__init__.py
rrmngmnt/common.py
rrmngmnt/db.py
rrmngmnt/errors.py
rrmngmnt/executor.py
rrmngmnt/filesystem.py
rrmngmnt/firewall.py
rrmngmnt/host.py
rrmngmnt/network.py
rrmngmnt/nmcli.py
rrmngmnt/operatingsystem.py
rrmngmnt/package_manager.py
rrmngmnt/playbook_runner.py
rrmngmnt/power_manager.py
rrmngmnt/resource.py
rrmngmnt/service.py
rrmngmnt/ssh.py
rrmngmnt/storage.py
rrmngmnt/user.py
python_rrmngmnt-0.2.1.dist-info/METADATA
python_rrmngmnt-0.2.1.dist-info/WHEEL
python_rrmngmnt-0.2.1.dist-info/licenses/AUTHORS
python_rrmngmnt-0.2.1.dist-info/licenses/LICENSE
python_rrmngmnt-0.2.1.dist-info/RECORD
