Metadata-Version: 2.4
Name: python-rrmngmnt
Version: 0.2.1
Summary: Tool to manage remote systems and services
Project-URL: Homepage, https://github.com/rhevm-qe-automation/python-rrmngmnt
Author-email: Lukas Bednar <lukyn17@gmail.com>
License: GPL-2.0-only
License-File: AUTHORS
License-File: LICENSE
Keywords: remote,resource,service
Classifier: Intended Audience :: Developers
Classifier: Intended Audience :: Information Technology
Classifier: Operating System :: POSIX
Classifier: Programming Language :: Python
Classifier: Programming Language :: Python :: 3
Classifier: Programming Language :: Python :: 3.9
Classifier: Programming Language :: Python :: 3.10
Classifier: Programming Language :: Python :: 3.11
Classifier: Programming Language :: Python :: 3.12
Classifier: Programming Language :: Python :: 3.13
Classifier: Programming Language :: Python :: 3.14
Classifier: Topic :: Utilities
Requires-Python: >=3.7
Requires-Dist: netaddr
Requires-Dist: paramiko
Requires-Dist: six
